{
  "formatVersion": 2,
  "exportedAt": "2026-04-16T13:39:43.105Z",
  "definition": {
    "id": "6854efaa-d83c-4554-be06-c9739f976f12",
    "metadata": {
      "documentName": "御見積書",
      "version": "1.0",
      "reportType": "general",
      "description": "Created: 2026-04-16T13:39:43.105Z | Updated: 2026-04-16T13:39:43.105Z",
      "sourceTemplateId": "quotation-modern"
    },
    "pageSettings": {
      "paperSize": "A4",
      "orientation": "portrait",
      "margins": {
        "top": 10,
        "right": 10,
        "bottom": 10,
        "left": 10
      },
      "unit": "mm"
    },
    "defaultTextStyle": {},
    "templateVariables": [],
    "calculationRules": [],
    "dataSources": [
      {
        "id": "eecdd3fa-3d1f-49bf-b6de-9399b1cbd901",
        "name": "見積書サンプルデータ",
        "fields": {
          "document.documentNo": "Q-2026-0001",
          "document.issueDate": "2026年4月16日",
          "document.registrationNo": "T1234567890123",
          "document.validUntil": "2026年5月16日",
          "document.deliveryTerms": "受注後2週間以内",
          "document.paymentTerms": "月末締め翌月末払い",
          "document.notes": "納品後30日以内にお支払いください。",
          "customer.customerName": "株式会社サンプル商事",
          "customer.postalCode": "100-0001",
          "customer.address": "東京都千代田区千代田1-1-1",
          "customer.contactPerson": "山田太郎",
          "summary.subtotal": 140000,
          "summary.tax10Base": 140000,
          "summary.tax10Amount": 14000,
          "summary.tax8Base": 0,
          "summary.tax8Amount": 0,
          "summary.totalIncTax": 154000,
          "items": [
            {
              "itemCode": "A-001",
              "itemName": "ウィジェットA",
              "quantity": 10,
              "unit": "個",
              "unitPrice": 5000,
              "amount": 50000
            },
            {
              "itemCode": "B-002",
              "itemName": "ウィジェットB（大）",
              "quantity": 5,
              "unit": "セット",
              "unitPrice": 12000,
              "amount": 60000
            },
            {
              "itemCode": "C-003",
              "itemName": "設置作業費",
              "quantity": 1,
              "unit": "式",
              "unitPrice": 30000,
              "amount": 30000
            }
          ]
        }
      }
    ],
    "outputVariants": [],
    "submissionModels": [],
    "validationRules": [],
    "pages": [
      {
        "id": "89f99afb-effb-4f7d-86e0-22fbbba65010",
        "name": "ページ 1",
        "width": 210,
        "height": 297,
        "background": "#ffffff",
        "sections": [
          {
            "id": "c1ebe117-5195-4944-a45c-4b87893577e9",
            "sectionType": "body",
            "height": 297,
            "elements": [
              {
                "id": "5aa72899-9b13-4595-81b1-aac637894a48",
                "type": "text",
                "position": {
                  "x": 10,
                  "y": 10
                },
                "size": {
                  "width": 100,
                  "height": 9
                },
                "zIndex": 3,
                "locked": true,
                "visible": true,
                "content": "御 見 積 書",
                "style": {
                  "fontSize": 7,
                  "textAlign": "left",
                  "verticalAlign": "middle",
                  "color": "#1a1a1a",
                  "fontWeight": "bold"
                },
                "name": "御 見 積 書"
              },
              {
                "id": "b7452bf2-9e75-4a04-bd33-aa09725c9b8b",
                "type": "shape",
                "position": {
                  "x": 10,
                  "y": 19
                },
                "size": {
                  "width": 80,
                  "height": 0.1
                },
                "zIndex": 1,
                "locked": true,
                "visible": true,
                "shape": "line",
                "stroke": "#3b82f6",
                "strokeWidth": 0.5,
                "name": "区切り線"
              },
              {
                "id": "f1efbd6c-70a7-47c2-ac41-bde2b5a6dbf8",
                "type": "tenantLogo",
                "position": {
                  "x": 175,
                  "y": 10
                },
                "size": {
                  "width": 25,
                  "height": 15
                },
                "zIndex": 3,
                "locked": false,
                "visible": true,
                "objectFit": "contain",
                "name": "自社ロゴ"
              },
              {
                "id": "025dba65-4833-44bf-9faa-ddaa3130f29e",
                "type": "tenantCompanyName",
                "position": {
                  "x": 120,
                  "y": 20
                },
                "size": {
                  "width": 50,
                  "height": 5
                },
                "zIndex": 3,
                "locked": false,
                "visible": true,
                "style": {
                  "fontSize": 4,
                  "fontWeight": "bold",
                  "color": "#1a1a1a"
                },
                "name": "自社名"
              },
              {
                "id": "98d5c953-ee95-4b7b-8b7d-00d3d57c7dca",
                "type": "tenantAddress",
                "position": {
                  "x": 120,
                  "y": 25
                },
                "size": {
                  "width": 80,
                  "height": 4
                },
                "zIndex": 3,
                "locked": false,
                "visible": true,
                "style": {
                  "fontSize": 2.5,
                  "color": "#666666"
                },
                "name": "自社住所"
              },
              {
                "id": "a8d9f08c-c3dc-4468-9752-e2e002d4d4d9",
                "type": "tenantPhone",
                "position": {
                  "x": 120,
                  "y": 29
                },
                "size": {
                  "width": 80,
                  "height": 4
                },
                "zIndex": 3,
                "locked": false,
                "visible": true,
                "style": {
                  "fontSize": 2.5,
                  "color": "#666666"
                },
                "name": "自社電話"
              },
              {
                "id": "799fd67f-f494-4a5f-aaec-518f05c8b92d",
                "type": "text",
                "position": {
                  "x": 10,
                  "y": 29
                },
                "size": {
                  "width": 20,
                  "height": 5
                },
                "zIndex": 3,
                "locked": true,
                "visible": true,
                "content": "見積番号:",
                "style": {
                  "fontSize": 2.8,
                  "textAlign": "left",
                  "verticalAlign": "middle",
                  "color": "#666666"
                },
                "name": "見積番号:"
              },
              {
                "id": "0abc1270-ed3e-45b8-b333-69c205beb15d",
                "type": "dataField",
                "position": {
                  "x": 30,
                  "y": 29
                },
                "size": {
                  "width": 60,
                  "height": 5
                },
                "zIndex": 3,
                "locked": false,
                "visible": true,
                "fieldKey": "document.documentNo",
                "fallbackText": "Q-2026-0001",
                "label": "Q-2026-0001",
                "style": {
                  "fontSize": 2.8,
                  "textAlign": "left",
                  "verticalAlign": "middle",
                  "color": "#1a1a1a"
                },
                "name": "書類番号"
              },
              {
                "id": "ed3f37f1-32f4-4028-965e-ebc68d1b6517",
                "type": "text",
                "position": {
                  "x": 10,
                  "y": 34
                },
                "size": {
                  "width": 20,
                  "height": 5
                },
                "zIndex": 3,
                "locked": true,
                "visible": true,
                "content": "発行日:",
                "style": {
                  "fontSize": 2.8,
                  "textAlign": "left",
                  "verticalAlign": "middle",
                  "color": "#666666"
                },
                "name": "発行日:"
              },
              {
                "id": "365801ec-c1e6-4905-9223-be10b9b80e99",
                "type": "dataField",
                "position": {
                  "x": 30,
                  "y": 34
                },
                "size": {
                  "width": 60,
                  "height": 5
                },
                "zIndex": 3,
                "locked": false,
                "visible": true,
                "fieldKey": "document.issueDate",
                "fallbackText": "2026年4月16日",
                "label": "2026年4月16日",
                "style": {
                  "fontSize": 2.8,
                  "textAlign": "left",
                  "verticalAlign": "middle",
                  "color": "#1a1a1a"
                },
                "name": "発行日"
              },
              {
                "id": "4f2604cc-bc7e-4084-814b-f6a4f9077a55",
                "type": "text",
                "position": {
                  "x": 10,
                  "y": 39
                },
                "size": {
                  "width": 20,
                  "height": 5
                },
                "zIndex": 3,
                "locked": true,
                "visible": true,
                "content": "登録番号:",
                "style": {
                  "fontSize": 2.8,
                  "textAlign": "left",
                  "verticalAlign": "middle",
                  "color": "#666666"
                },
                "name": "登録番号:"
              },
              {
                "id": "e3e7fb6f-1fb5-4e1b-88e0-57b00697eb61",
                "type": "dataField",
                "position": {
                  "x": 30,
                  "y": 39
                },
                "size": {
                  "width": 60,
                  "height": 5
                },
                "zIndex": 3,
                "locked": false,
                "visible": true,
                "fieldKey": "document.registrationNo",
                "fallbackText": "T1234567890123",
                "label": "T1234567890123",
                "style": {
                  "fontSize": 2.8,
                  "textAlign": "left",
                  "verticalAlign": "middle",
                  "color": "#1a1a1a"
                },
                "name": "登録番号"
              },
              {
                "id": "8fbf7491-d00e-4335-b16d-fd9bf7173083",
                "type": "dataField",
                "position": {
                  "x": 10,
                  "y": 46
                },
                "size": {
                  "width": 100,
                  "height": 6
                },
                "zIndex": 3,
                "locked": false,
                "visible": true,
                "fieldKey": "customer.customerName",
                "fallbackText": "株式会社サンプル商事",
                "label": "株式会社サンプル商事",
                "style": {
                  "fontSize": 4,
                  "textAlign": "left",
                  "verticalAlign": "middle",
                  "color": "#1a1a1a",
                  "fontWeight": "bold"
                },
                "name": "顧客名"
              },
              {
                "id": "e5085ca2-418f-4721-a29b-feab16bba9d4",
                "type": "text",
                "position": {
                  "x": 110,
                  "y": 46
                },
                "size": {
                  "width": 10,
                  "height": 6
                },
                "zIndex": 3,
                "locked": true,
                "visible": true,
                "content": "御中",
                "style": {
                  "fontSize": 4,
                  "textAlign": "left",
                  "verticalAlign": "middle",
                  "color": "#1a1a1a"
                },
                "name": "御中"
              },
              {
                "id": "1b97e741-01c0-457c-a241-dc707636ad2e",
                "type": "shape",
                "position": {
                  "x": 10,
                  "y": 52
                },
                "size": {
                  "width": 110,
                  "height": 0.1
                },
                "zIndex": 1,
                "locked": true,
                "visible": true,
                "shape": "line",
                "stroke": "#1a1a1a",
                "strokeWidth": 0.3,
                "name": "区切り線"
              },
              {
                "id": "55004a70-eeb3-46f8-bd27-ad529f65d620",
                "type": "text",
                "position": {
                  "x": 10,
                  "y": 52
                },
                "size": {
                  "width": 5,
                  "height": 5
                },
                "zIndex": 3,
                "locked": true,
                "visible": true,
                "content": "〒",
                "style": {
                  "fontSize": 2.5,
                  "textAlign": "left",
                  "verticalAlign": "middle",
                  "color": "#666666"
                },
                "name": "〒"
              },
              {
                "id": "3b8dc6ed-399c-4497-99fc-ea9eee60e62d",
                "type": "dataField",
                "position": {
                  "x": 15,
                  "y": 52
                },
                "size": {
                  "width": 30,
                  "height": 5
                },
                "zIndex": 3,
                "locked": false,
                "visible": true,
                "fieldKey": "customer.postalCode",
                "fallbackText": "100-0001",
                "label": "100-0001",
                "style": {
                  "fontSize": 2.5,
                  "textAlign": "left",
                  "verticalAlign": "middle",
                  "color": "#1a1a1a"
                },
                "name": "郵便番号"
              },
              {
                "id": "6692c495-b8d1-4cba-a394-1535e588e39b",
                "type": "dataField",
                "position": {
                  "x": 10,
                  "y": 57
                },
                "size": {
                  "width": 110,
                  "height": 5
                },
                "zIndex": 3,
                "locked": false,
                "visible": true,
                "fieldKey": "customer.address",
                "fallbackText": "東京都千代田区千代田1-1-1",
                "label": "東京都千代田区千代田1-1-1",
                "style": {
                  "fontSize": 2.5,
                  "textAlign": "left",
                  "verticalAlign": "middle",
                  "color": "#1a1a1a"
                },
                "name": "住所"
              },
              {
                "id": "8ac83844-16a6-4872-9b5c-33923a2a4ca7",
                "type": "text",
                "position": {
                  "x": 10,
                  "y": 62
                },
                "size": {
                  "width": 15,
                  "height": 5
                },
                "zIndex": 3,
                "locked": true,
                "visible": true,
                "content": "ご担当:",
                "style": {
                  "fontSize": 2.5,
                  "textAlign": "left",
                  "verticalAlign": "middle",
                  "color": "#666666"
                },
                "name": "ご担当:"
              },
              {
                "id": "15c2ba18-dc7e-4b28-93f8-ba759b743d65",
                "type": "dataField",
                "position": {
                  "x": 25,
                  "y": 62
                },
                "size": {
                  "width": 50,
                  "height": 5
                },
                "zIndex": 3,
                "locked": false,
                "visible": true,
                "fieldKey": "customer.contactPerson",
                "fallbackText": "山田太郎",
                "label": "山田太郎",
                "style": {
                  "fontSize": 2.5,
                  "textAlign": "left",
                  "verticalAlign": "middle",
                  "color": "#1a1a1a"
                },
                "name": "担当者名"
              },
              {
                "id": "65fe5b37-950d-43fd-951d-c94f9d0eeeec",
                "type": "text",
                "position": {
                  "x": 75,
                  "y": 62
                },
                "size": {
                  "width": 8,
                  "height": 5
                },
                "zIndex": 3,
                "locked": true,
                "visible": true,
                "content": "様",
                "style": {
                  "fontSize": 2.5,
                  "textAlign": "left",
                  "verticalAlign": "middle",
                  "color": "#1a1a1a"
                },
                "name": "様"
              },
              {
                "id": "f0535fbd-ad55-465b-9e63-46cc19c58c19",
                "type": "shape",
                "position": {
                  "x": 10,
                  "y": 69
                },
                "size": {
                  "width": 190,
                  "height": 10
                },
                "zIndex": 1,
                "locked": true,
                "visible": true,
                "shape": "rectangle",
                "fill": "#f0f7ff",
                "stroke": "#3b82f6",
                "strokeWidth": 0.3,
                "borderRadius": 2,
                "name": "背景ボックス"
              },
              {
                "id": "5f633600-5c19-4ea5-8eb2-5af7d2d3d974",
                "type": "text",
                "position": {
                  "x": 14,
                  "y": 69
                },
                "size": {
                  "width": 40,
                  "height": 10
                },
                "zIndex": 3,
                "locked": true,
                "visible": true,
                "content": "合計金額（税込）",
                "style": {
                  "fontSize": 3,
                  "textAlign": "left",
                  "verticalAlign": "middle",
                  "color": "#3b82f6",
                  "fontWeight": "bold"
                },
                "name": "合計金額（税込）"
              },
              {
                "id": "b50e8732-7d3d-4a92-af8e-6a67fb49d65c",
                "type": "dataField",
                "position": {
                  "x": 54,
                  "y": 69
                },
                "size": {
                  "width": 142,
                  "height": 10
                },
                "zIndex": 3,
                "locked": false,
                "visible": true,
                "fieldKey": "summary.totalIncTax",
                "format": {
                  "type": "currency_jpy"
                },
                "fallbackText": "¥154,000",
                "label": "¥154,000",
                "style": {
                  "fontSize": 5,
                  "textAlign": "right",
                  "verticalAlign": "middle",
                  "color": "#1a1a1a",
                  "fontWeight": "bold"
                },
                "name": "合計金額（税込）"
              },
              {
                "id": "743f5ea1-aeb9-48d1-bcd7-6c9d38952800",
                "type": "repeatingBand",
                "position": {
                  "x": 10,
                  "y": 83
                },
                "size": {
                  "width": 190,
                  "height": 77
                },
                "zIndex": 2,
                "locked": false,
                "visible": true,
                "dataSource": "items",
                "itemHeight": 7,
                "showHeader": true,
                "showFooter": false,
                "maxItems": 10,
                "showEmptyRowLines": true,
                "pageBreak": "none",
                "totals": [],
                "oddRowColor": "#ffffff",
                "evenRowColor": "#fafafa",
                "borderColor": "#e0e0e0",
                "borderWidth": 0.2,
                "headerStyle": {
                  "fontSize": 2.8,
                  "fontWeight": "bold",
                  "color": "#333333",
                  "backgroundColor": "#f5f5f5"
                },
                "style": {
                  "fontSize": 2.8,
                  "color": "#1a1a1a"
                },
                "fields": [
                  {
                    "key": "itemCode",
                    "label": "品番",
                    "width": 28,
                    "align": "left"
                  },
                  {
                    "key": "itemName",
                    "label": "品名",
                    "width": 72,
                    "align": "left"
                  },
                  {
                    "key": "quantity",
                    "label": "数量",
                    "width": 18,
                    "align": "right",
                    "format": {
                      "type": "comma"
                    }
                  },
                  {
                    "key": "unit",
                    "label": "単位",
                    "width": 14,
                    "align": "center"
                  },
                  {
                    "key": "unitPrice",
                    "label": "単価",
                    "width": 28,
                    "align": "right",
                    "format": {
                      "type": "currency_jpy"
                    }
                  },
                  {
                    "key": "amount",
                    "label": "金額",
                    "width": 30,
                    "align": "right",
                    "format": {
                      "type": "currency_jpy"
                    }
                  }
                ],
                "name": "明細テーブル"
              },
              {
                "id": "cd08f048-36c4-47f4-ad06-c275ecc697a1",
                "type": "shape",
                "position": {
                  "x": 120,
                  "y": 163
                },
                "size": {
                  "width": 80,
                  "height": 42
                },
                "zIndex": 1,
                "locked": true,
                "visible": true,
                "shape": "rectangle",
                "fill": "transparent",
                "stroke": "#e0e0e0",
                "strokeWidth": 0.2,
                "name": "枠線"
              },
              {
                "id": "d512d2e0-f5bd-4883-8522-cf98d2a6c147",
                "type": "text",
                "position": {
                  "x": 122,
                  "y": 163
                },
                "size": {
                  "width": 36,
                  "height": 7
                },
                "zIndex": 3,
                "locked": true,
                "visible": true,
                "content": "小計",
                "style": {
                  "fontSize": 2.8,
                  "textAlign": "left",
                  "verticalAlign": "middle",
                  "color": "#1a1a1a",
                  "fontWeight": "normal"
                },
                "name": "小計"
              },
              {
                "id": "a852763d-17ef-46c7-836d-d8713f7454d2",
                "type": "dataField",
                "position": {
                  "x": 162,
                  "y": 163
                },
                "size": {
                  "width": 36,
                  "height": 7
                },
                "zIndex": 3,
                "locked": false,
                "visible": true,
                "fieldKey": "summary.subtotal",
                "format": {
                  "type": "currency_jpy"
                },
                "fallbackText": "¥0",
                "label": "¥0",
                "style": {
                  "fontSize": 2.8,
                  "textAlign": "right",
                  "verticalAlign": "middle",
                  "color": "#1a1a1a",
                  "fontWeight": "normal"
                },
                "name": "小計"
              },
              {
                "id": "476a726d-a68f-462a-9114-45daa423af85",
                "type": "shape",
                "position": {
                  "x": 120,
                  "y": 170
                },
                "size": {
                  "width": 80,
                  "height": 0.1
                },
                "zIndex": 1,
                "locked": true,
                "visible": true,
                "shape": "line",
                "stroke": "#e0e0e0",
                "strokeWidth": 0.2,
                "name": "区切り線"
              },
              {
                "id": "555100dd-0457-4a72-8c43-a1d853685d29",
                "type": "text",
                "position": {
                  "x": 122,
                  "y": 170
                },
                "size": {
                  "width": 36,
                  "height": 7
                },
                "zIndex": 3,
                "locked": true,
                "visible": true,
                "content": "10%対象",
                "style": {
                  "fontSize": 2.8,
                  "textAlign": "left",
                  "verticalAlign": "middle",
                  "color": "#1a1a1a",
                  "fontWeight": "normal"
                },
                "name": "10%対象"
              },
              {
                "id": "6367fb00-43a9-448c-acb1-6cdb3e2bbffa",
                "type": "dataField",
                "position": {
                  "x": 162,
                  "y": 170
                },
                "size": {
                  "width": 36,
                  "height": 7
                },
                "zIndex": 3,
                "locked": false,
                "visible": true,
                "fieldKey": "summary.tax10Base",
                "format": {
                  "type": "currency_jpy"
                },
                "fallbackText": "¥0",
                "label": "¥0",
                "style": {
                  "fontSize": 2.8,
                  "textAlign": "right",
                  "verticalAlign": "middle",
                  "color": "#1a1a1a",
                  "fontWeight": "normal"
                },
                "name": "10%対象額"
              },
              {
                "id": "6ab0be2d-5f2e-482c-90c6-4a31af0cb590",
                "type": "shape",
                "position": {
                  "x": 120,
                  "y": 177
                },
                "size": {
                  "width": 80,
                  "height": 0.1
                },
                "zIndex": 1,
                "locked": true,
                "visible": true,
                "shape": "line",
                "stroke": "#e0e0e0",
                "strokeWidth": 0.2,
                "name": "区切り線"
              },
              {
                "id": "605c312f-4822-4a31-b0c3-c950cf1819a3",
                "type": "text",
                "position": {
                  "x": 122,
                  "y": 177
                },
                "size": {
                  "width": 36,
                  "height": 7
                },
                "zIndex": 3,
                "locked": true,
                "visible": true,
                "content": "消費税（10%）",
                "style": {
                  "fontSize": 2.8,
                  "textAlign": "left",
                  "verticalAlign": "middle",
                  "color": "#1a1a1a",
                  "fontWeight": "normal"
                },
                "name": "消費税（10%）"
              },
              {
                "id": "0fcc7523-d39c-4fc2-977d-12b104337070",
                "type": "dataField",
                "position": {
                  "x": 162,
                  "y": 177
                },
                "size": {
                  "width": 36,
                  "height": 7
                },
                "zIndex": 3,
                "locked": false,
                "visible": true,
                "fieldKey": "summary.tax10Amount",
                "format": {
                  "type": "currency_jpy"
                },
                "fallbackText": "¥0",
                "label": "¥0",
                "style": {
                  "fontSize": 2.8,
                  "textAlign": "right",
                  "verticalAlign": "middle",
                  "color": "#1a1a1a",
                  "fontWeight": "normal"
                },
                "name": "消費税（10%）"
              },
              {
                "id": "6f530fe3-6297-4ebf-9a66-f0f54c24af22",
                "type": "shape",
                "position": {
                  "x": 120,
                  "y": 184
                },
                "size": {
                  "width": 80,
                  "height": 0.1
                },
                "zIndex": 1,
                "locked": true,
                "visible": true,
                "shape": "line",
                "stroke": "#e0e0e0",
                "strokeWidth": 0.2,
                "name": "区切り線"
              },
              {
                "id": "0e3d655f-b725-4f22-98d7-42aba80a2729",
                "type": "text",
                "position": {
                  "x": 122,
                  "y": 184
                },
                "size": {
                  "width": 36,
                  "height": 7
                },
                "zIndex": 3,
                "locked": true,
                "visible": true,
                "content": "8%対象",
                "style": {
                  "fontSize": 2.8,
                  "textAlign": "left",
                  "verticalAlign": "middle",
                  "color": "#1a1a1a",
                  "fontWeight": "normal"
                },
                "name": "8%対象"
              },
              {
                "id": "4c06fe79-0e31-46a3-90d2-6e38e113caf0",
                "type": "dataField",
                "position": {
                  "x": 162,
                  "y": 184
                },
                "size": {
                  "width": 36,
                  "height": 7
                },
                "zIndex": 3,
                "locked": false,
                "visible": true,
                "fieldKey": "summary.tax8Base",
                "format": {
                  "type": "currency_jpy"
                },
                "fallbackText": "¥0",
                "label": "¥0",
                "style": {
                  "fontSize": 2.8,
                  "textAlign": "right",
                  "verticalAlign": "middle",
                  "color": "#1a1a1a",
                  "fontWeight": "normal"
                },
                "name": "8%対象額"
              },
              {
                "id": "7811d2e9-ede7-4bb0-9cba-8881a28bcf2e",
                "type": "shape",
                "position": {
                  "x": 120,
                  "y": 191
                },
                "size": {
                  "width": 80,
                  "height": 0.1
                },
                "zIndex": 1,
                "locked": true,
                "visible": true,
                "shape": "line",
                "stroke": "#e0e0e0",
                "strokeWidth": 0.2,
                "name": "区切り線"
              },
              {
                "id": "2be94f92-088e-4c41-8507-1a580777e706",
                "type": "text",
                "position": {
                  "x": 122,
                  "y": 191
                },
                "size": {
                  "width": 36,
                  "height": 7
                },
                "zIndex": 3,
                "locked": true,
                "visible": true,
                "content": "消費税（8%）",
                "style": {
                  "fontSize": 2.8,
                  "textAlign": "left",
                  "verticalAlign": "middle",
                  "color": "#1a1a1a",
                  "fontWeight": "normal"
                },
                "name": "消費税（8%）"
              },
              {
                "id": "907193ca-f74d-4695-bc18-ee87d43c536c",
                "type": "dataField",
                "position": {
                  "x": 162,
                  "y": 191
                },
                "size": {
                  "width": 36,
                  "height": 7
                },
                "zIndex": 3,
                "locked": false,
                "visible": true,
                "fieldKey": "summary.tax8Amount",
                "format": {
                  "type": "currency_jpy"
                },
                "fallbackText": "¥0",
                "label": "¥0",
                "style": {
                  "fontSize": 2.8,
                  "textAlign": "right",
                  "verticalAlign": "middle",
                  "color": "#1a1a1a",
                  "fontWeight": "normal"
                },
                "name": "消費税（8%）"
              },
              {
                "id": "ef5e3ea7-d745-4f8b-a745-b70ea1dba90c",
                "type": "shape",
                "position": {
                  "x": 120,
                  "y": 198
                },
                "size": {
                  "width": 80,
                  "height": 0.1
                },
                "zIndex": 1,
                "locked": true,
                "visible": true,
                "shape": "line",
                "stroke": "#e0e0e0",
                "strokeWidth": 0.2,
                "name": "区切り線"
              },
              {
                "id": "1cf49328-6e82-47d4-a03e-832b5f3cfb8a",
                "type": "shape",
                "position": {
                  "x": 120,
                  "y": 198
                },
                "size": {
                  "width": 80,
                  "height": 7
                },
                "zIndex": 1,
                "locked": true,
                "visible": true,
                "shape": "rectangle",
                "fill": "#f0f7ff",
                "stroke": "#e0e0e0",
                "strokeWidth": 0.2,
                "name": "背景ボックス"
              },
              {
                "id": "4ecf2323-1cbb-4be6-a01c-a7e6163737d9",
                "type": "text",
                "position": {
                  "x": 122,
                  "y": 198
                },
                "size": {
                  "width": 36,
                  "height": 7
                },
                "zIndex": 3,
                "locked": true,
                "visible": true,
                "content": "合計（税込）",
                "style": {
                  "fontSize": 2.8,
                  "textAlign": "left",
                  "verticalAlign": "middle",
                  "color": "#1a1a1a",
                  "fontWeight": "bold"
                },
                "name": "合計（税込）"
              },
              {
                "id": "ddc5d6cd-03de-4554-8841-59e55cca8e54",
                "type": "dataField",
                "position": {
                  "x": 162,
                  "y": 198
                },
                "size": {
                  "width": 36,
                  "height": 7
                },
                "zIndex": 3,
                "locked": false,
                "visible": true,
                "fieldKey": "summary.totalIncTax",
                "format": {
                  "type": "currency_jpy"
                },
                "fallbackText": "¥0",
                "label": "¥0",
                "style": {
                  "fontSize": 2.8,
                  "textAlign": "right",
                  "verticalAlign": "middle",
                  "color": "#1a1a1a",
                  "fontWeight": "bold"
                },
                "name": "合計金額（税込）"
              },
              {
                "id": "3c01bff2-c262-4404-bcc2-265b6aa0b9f2",
                "type": "text",
                "position": {
                  "x": 10,
                  "y": 210
                },
                "size": {
                  "width": 24,
                  "height": 6
                },
                "zIndex": 3,
                "locked": true,
                "visible": true,
                "content": "有効期限:",
                "style": {
                  "fontSize": 2.8,
                  "textAlign": "left",
                  "verticalAlign": "middle",
                  "color": "#666666"
                },
                "name": "有効期限:"
              },
              {
                "id": "b6ca391c-397d-4b34-b7e8-f5f547db1e50",
                "type": "dataField",
                "position": {
                  "x": 34,
                  "y": 210
                },
                "size": {
                  "width": 70,
                  "height": 6
                },
                "zIndex": 3,
                "locked": false,
                "visible": true,
                "fieldKey": "document.validUntil",
                "fallbackText": "発行日より1ヶ月",
                "label": "発行日より1ヶ月",
                "style": {
                  "fontSize": 2.8,
                  "textAlign": "left",
                  "verticalAlign": "middle",
                  "color": "#1a1a1a"
                },
                "name": "有効期限"
              },
              {
                "id": "faf2f95d-cc35-46e3-86fc-f4ff3d30c700",
                "type": "text",
                "position": {
                  "x": 10,
                  "y": 216
                },
                "size": {
                  "width": 24,
                  "height": 6
                },
                "zIndex": 3,
                "locked": true,
                "visible": true,
                "content": "納品条件:",
                "style": {
                  "fontSize": 2.8,
                  "textAlign": "left",
                  "verticalAlign": "middle",
                  "color": "#666666"
                },
                "name": "納品条件:"
              },
              {
                "id": "9d020c85-19af-4042-9e6a-b7462f6fc394",
                "type": "dataField",
                "position": {
                  "x": 34,
                  "y": 216
                },
                "size": {
                  "width": 70,
                  "height": 6
                },
                "zIndex": 3,
                "locked": false,
                "visible": true,
                "fieldKey": "document.deliveryTerms",
                "fallbackText": "受注後2週間以内",
                "label": "受注後2週間以内",
                "style": {
                  "fontSize": 2.8,
                  "textAlign": "left",
                  "verticalAlign": "middle",
                  "color": "#1a1a1a"
                },
                "name": "納品条件"
              },
              {
                "id": "f54a35c2-f3cb-4ff6-a368-dfae67ebe4ed",
                "type": "text",
                "position": {
                  "x": 10,
                  "y": 222
                },
                "size": {
                  "width": 24,
                  "height": 6
                },
                "zIndex": 3,
                "locked": true,
                "visible": true,
                "content": "支払条件:",
                "style": {
                  "fontSize": 2.8,
                  "textAlign": "left",
                  "verticalAlign": "middle",
                  "color": "#666666"
                },
                "name": "支払条件:"
              },
              {
                "id": "03f1d510-baf3-43d7-8ec1-bb58931f062a",
                "type": "dataField",
                "position": {
                  "x": 34,
                  "y": 222
                },
                "size": {
                  "width": 70,
                  "height": 6
                },
                "zIndex": 3,
                "locked": false,
                "visible": true,
                "fieldKey": "document.paymentTerms",
                "fallbackText": "月末締め翌月末払い",
                "label": "月末締め翌月末払い",
                "style": {
                  "fontSize": 2.8,
                  "textAlign": "left",
                  "verticalAlign": "middle",
                  "color": "#1a1a1a"
                },
                "name": "支払条件"
              },
              {
                "id": "1eb57bc3-8e6f-447a-b021-c64717373170",
                "type": "shape",
                "position": {
                  "x": 10,
                  "y": 233
                },
                "size": {
                  "width": 190,
                  "height": 30
                },
                "zIndex": 1,
                "locked": true,
                "visible": true,
                "shape": "rectangle",
                "fill": "transparent",
                "stroke": "#e0e0e0",
                "strokeWidth": 0.2,
                "name": "枠線"
              },
              {
                "id": "fafbf4ef-8133-4166-b75d-90724e89146c",
                "type": "text",
                "position": {
                  "x": 12,
                  "y": 233
                },
                "size": {
                  "width": 20,
                  "height": 6
                },
                "zIndex": 3,
                "locked": true,
                "visible": true,
                "content": "備考",
                "style": {
                  "fontSize": 2.8,
                  "textAlign": "left",
                  "verticalAlign": "middle",
                  "color": "#666666",
                  "fontWeight": "bold"
                },
                "name": "備考"
              },
              {
                "id": "e3a74af1-964f-476f-af3d-0e156408466c",
                "type": "dataField",
                "position": {
                  "x": 12,
                  "y": 239
                },
                "size": {
                  "width": 186,
                  "height": 22
                },
                "zIndex": 3,
                "locked": false,
                "visible": true,
                "fieldKey": "document.notes",
                "fallbackText": "",
                "label": "",
                "style": {
                  "fontSize": 2.5,
                  "textAlign": "left",
                  "verticalAlign": "top",
                  "color": "#1a1a1a"
                },
                "name": "備考テキスト"
              }
            ]
          }
        ],
        "groups": [
          {
            "id": "grp-f275890f",
            "name": "タイトル",
            "elementIds": [
              "5aa72899-9b13-4595-81b1-aac637894a48",
              "b7452bf2-9e75-4a04-bd33-aa09725c9b8b"
            ],
            "collapsed": true,
            "visible": true,
            "locked": false
          },
          {
            "id": "grp-afd2cf64",
            "name": "自社情報",
            "elementIds": [
              "f1efbd6c-70a7-47c2-ac41-bde2b5a6dbf8",
              "025dba65-4833-44bf-9faa-ddaa3130f29e",
              "98d5c953-ee95-4b7b-8b7d-00d3d57c7dca",
              "a8d9f08c-c3dc-4468-9752-e2e002d4d4d9"
            ],
            "collapsed": true,
            "visible": true,
            "locked": false
          },
          {
            "id": "grp-11fdcaf0",
            "name": "書類情報",
            "elementIds": [
              "799fd67f-f494-4a5f-aaec-518f05c8b92d",
              "0abc1270-ed3e-45b8-b333-69c205beb15d",
              "ed3f37f1-32f4-4028-965e-ebc68d1b6517",
              "365801ec-c1e6-4905-9223-be10b9b80e99",
              "4f2604cc-bc7e-4084-814b-f6a4f9077a55",
              "e3e7fb6f-1fb5-4e1b-88e0-57b00697eb61"
            ],
            "collapsed": true,
            "visible": true,
            "locked": false
          },
          {
            "id": "grp-84d0b961",
            "name": "宛先",
            "elementIds": [
              "8fbf7491-d00e-4335-b16d-fd9bf7173083",
              "e5085ca2-418f-4721-a29b-feab16bba9d4",
              "1b97e741-01c0-457c-a241-dc707636ad2e",
              "55004a70-eeb3-46f8-bd27-ad529f65d620",
              "3b8dc6ed-399c-4497-99fc-ea9eee60e62d",
              "6692c495-b8d1-4cba-a394-1535e588e39b",
              "8ac83844-16a6-4872-9b5c-33923a2a4ca7",
              "15c2ba18-dc7e-4b28-93f8-ba759b743d65",
              "65fe5b37-950d-43fd-951d-c94f9d0eeeec"
            ],
            "collapsed": true,
            "visible": true,
            "locked": false
          },
          {
            "id": "grp-cbb787af",
            "name": "合計金額",
            "elementIds": [
              "f0535fbd-ad55-465b-9e63-46cc19c58c19",
              "5f633600-5c19-4ea5-8eb2-5af7d2d3d974",
              "b50e8732-7d3d-4a92-af8e-6a67fb49d65c"
            ],
            "collapsed": true,
            "visible": true,
            "locked": false
          },
          {
            "id": "grp-b20506b3",
            "name": "明細テーブル",
            "elementIds": [
              "743f5ea1-aeb9-48d1-bcd7-6c9d38952800"
            ],
            "collapsed": true,
            "visible": true,
            "locked": false
          },
          {
            "id": "grp-655b15a5",
            "name": "税額内訳",
            "elementIds": [
              "cd08f048-36c4-47f4-ad06-c275ecc697a1",
              "d512d2e0-f5bd-4883-8522-cf98d2a6c147",
              "a852763d-17ef-46c7-836d-d8713f7454d2",
              "476a726d-a68f-462a-9114-45daa423af85",
              "555100dd-0457-4a72-8c43-a1d853685d29",
              "6367fb00-43a9-448c-acb1-6cdb3e2bbffa",
              "6ab0be2d-5f2e-482c-90c6-4a31af0cb590",
              "605c312f-4822-4a31-b0c3-c950cf1819a3",
              "0fcc7523-d39c-4fc2-977d-12b104337070",
              "6f530fe3-6297-4ebf-9a66-f0f54c24af22",
              "0e3d655f-b725-4f22-98d7-42aba80a2729",
              "4c06fe79-0e31-46a3-90d2-6e38e113caf0",
              "7811d2e9-ede7-4bb0-9cba-8881a28bcf2e",
              "2be94f92-088e-4c41-8507-1a580777e706",
              "907193ca-f74d-4695-bc18-ee87d43c536c",
              "ef5e3ea7-d745-4f8b-a745-b70ea1dba90c",
              "1cf49328-6e82-47d4-a03e-832b5f3cfb8a",
              "4ecf2323-1cbb-4be6-a01c-a7e6163737d9",
              "ddc5d6cd-03de-4554-8841-59e55cca8e54"
            ],
            "collapsed": true,
            "visible": true,
            "locked": false
          },
          {
            "id": "grp-1281fd61",
            "name": "取引条件",
            "elementIds": [
              "3c01bff2-c262-4404-bcc2-265b6aa0b9f2",
              "b6ca391c-397d-4b34-b7e8-f5f547db1e50",
              "faf2f95d-cc35-46e3-86fc-f4ff3d30c700",
              "9d020c85-19af-4042-9e6a-b7462f6fc394",
              "f54a35c2-f3cb-4ff6-a368-dfae67ebe4ed",
              "03f1d510-baf3-43d7-8ec1-bb58931f062a"
            ],
            "collapsed": true,
            "visible": true,
            "locked": false
          },
          {
            "id": "grp-dc693cb3",
            "name": "備考",
            "elementIds": [
              "1eb57bc3-8e6f-447a-b021-c64717373170",
              "fafbf4ef-8133-4166-b75d-90724e89146c",
              "e3a74af1-964f-476f-af3d-0e156408466c"
            ],
            "collapsed": true,
            "visible": true,
            "locked": false
          }
        ]
      }
    ],
    "schema": {
      "groups": [
        {
          "id": "qm-grp-doc",
          "label": "見積情報",
          "role": "master",
          "dataKey": "document",
          "fields": [
            {
              "id": "qm-f-doc-no",
              "key": "documentNo",
              "label": "見積番号",
              "type": "string"
            },
            {
              "id": "qm-f-issue-date",
              "key": "issueDate",
              "label": "発行日",
              "type": "date"
            },
            {
              "id": "qm-f-reg-no",
              "key": "registrationNo",
              "label": "登録番号",
              "type": "string"
            },
            {
              "id": "qm-f-valid-until",
              "key": "validUntil",
              "label": "有効期限",
              "type": "date"
            },
            {
              "id": "qm-f-delivery-terms",
              "key": "deliveryTerms",
              "label": "納品条件",
              "type": "string"
            },
            {
              "id": "qm-f-payment-terms",
              "key": "paymentTerms",
              "label": "支払条件",
              "type": "string"
            },
            {
              "id": "qm-f-notes",
              "key": "notes",
              "label": "備考",
              "type": "string"
            }
          ]
        },
        {
          "id": "qm-grp-customer",
          "label": "顧客情報",
          "role": "master",
          "dataKey": "customer",
          "fields": [
            {
              "id": "qm-f-cust-name",
              "key": "customerName",
              "label": "顧客名",
              "type": "string"
            },
            {
              "id": "qm-f-postal",
              "key": "postalCode",
              "label": "郵便番号",
              "type": "string"
            },
            {
              "id": "qm-f-address",
              "key": "address",
              "label": "住所",
              "type": "string"
            },
            {
              "id": "qm-f-contact",
              "key": "contactPerson",
              "label": "担当者",
              "type": "string"
            }
          ]
        },
        {
          "id": "qm-grp-items",
          "label": "明細",
          "role": "detail",
          "dataKey": "items",
          "fields": [
            {
              "id": "qm-f-code",
              "key": "itemCode",
              "label": "品番",
              "type": "string"
            },
            {
              "id": "qm-f-name",
              "key": "itemName",
              "label": "品名",
              "type": "string"
            },
            {
              "id": "qm-f-qty",
              "key": "quantity",
              "label": "数量",
              "type": "number"
            },
            {
              "id": "qm-f-unit",
              "key": "unit",
              "label": "単位",
              "type": "string"
            },
            {
              "id": "qm-f-price",
              "key": "unitPrice",
              "label": "単価",
              "type": "number"
            },
            {
              "id": "qm-f-amount",
              "key": "amount",
              "label": "金額",
              "type": "number"
            }
          ]
        },
        {
          "id": "qm-grp-summary",
          "label": "集計情報",
          "role": "master",
          "dataKey": "summary",
          "fields": [
            {
              "id": "qm-f-subtotal",
              "key": "subtotal",
              "label": "小計",
              "type": "number"
            },
            {
              "id": "qm-f-tax10-base",
              "key": "tax10Base",
              "label": "10%対象",
              "type": "number"
            },
            {
              "id": "qm-f-tax10-amt",
              "key": "tax10Amount",
              "label": "消費税(10%)",
              "type": "number"
            },
            {
              "id": "qm-f-tax8-base",
              "key": "tax8Base",
              "label": "8%対象",
              "type": "number"
            },
            {
              "id": "qm-f-tax8-amt",
              "key": "tax8Amount",
              "label": "消費税(8%)",
              "type": "number"
            },
            {
              "id": "qm-f-total",
              "key": "totalIncTax",
              "label": "合計(税込)",
              "type": "number"
            }
          ]
        }
      ]
    }
  }
}